get_comics/__init__.py
get_comics/__main__.py
get_comics/library.txt
get_comics-0.1.0.dist-info/LICENSE
get_comics-0.1.0.dist-info/METADATA
get_comics-0.1.0.dist-info/WHEEL
get_comics-0.1.0.dist-info/entry_points.txt
get_comics-0.1.0.dist-info/top_level.txt
get_comics-0.1.0.dist-info/RECORD
