Metadata-Version: 2.1
Name: get-comics
Version: 0.1.0
Summary: A comicbook scrapper
Home-page: UNKNOWN
Author: Loris M
Author-email: 
License: UNKNOWN
Platform: UNKNOWN
Classifier: Programming Language :: Python :: 3
Classifier: License :: OSI Approved :: MIT License
Classifier: Operating System :: OS Independent
Requires-Python: >=3.6
